CHANGES.txt
bootstrap.py
buildout.cfg
setup.py
src/megrok/__init__.py
src/megrok.resourcelibrary.egg-info/PKG-INFO
src/megrok.resourcelibrary.egg-info/SOURCES.txt
src/megrok.resourcelibrary.egg-info/dependency_links.txt
src/megrok.resourcelibrary.egg-info/entry_points.txt
src/megrok.resourcelibrary.egg-info/namespace_packages.txt
src/megrok.resourcelibrary.egg-info/not-zip-safe
src/megrok.resourcelibrary.egg-info/requires.txt
src/megrok.resourcelibrary.egg-info/top_level.txt
src/megrok/resourcelibrary/README.txt
src/megrok/resourcelibrary/__init__.py
src/megrok/resourcelibrary/components.py
src/megrok/resourcelibrary/directive.py
src/megrok/resourcelibrary/meta.py
src/megrok/resourcelibrary/meta.zcml
src/megrok/resourcelibrary/tests/__init__.py
src/megrok/resourcelibrary/tests/ftesting.zcml
src/megrok/resourcelibrary/tests/tests.py
src/megrok/resourcelibrary/tests/example/1.js
src/megrok/resourcelibrary/tests/example/2.css
src/megrok/resourcelibrary/tests/example/3.kss
src/megrok/resourcelibrary/tests/example/my-lib/included.css
src/megrok/resourcelibrary/tests/example/my-lib/included.js
src/megrok/resourcelibrary/tests/example/my-lib/included.kss