Metadata-Version: 1.0
Name: megrok.resourcelibrary
Version: 0.9.1
Summary: Static resource library support for Grok.
Home-page: UNKNOWN
Author: Grok Team
Author-email: grok-dev@zope.org
License: ZPL
Platform: UNKNOWN
Classifier: Programming Language :: Python
Classifier: Topic :: Software Development :: Libraries :: Python Modules
